{"17268":["DE","17268","Flieth-Stegelitz","Brandenburg","BB","","00","Landkreis Uckermark","12073","53.1417","13.8333",""],"17279":["DE","17279","Lychen","Brandenburg","BB","","00","Landkreis Uckermark","12073","53.2124","13.3148","4"],"17291":["DE","17291","G\u00f6ritz","Brandenburg","BB","","00","Landkreis Uckermark","12073","53.4063","13.9156","4"],"17326":["DE","17326","Br\u00fcssow","Brandenburg","BB","","00","Landkreis Uckermark","12073","53.3997","14.1253","4"],"17337":["DE","17337","Gro\u00df Luckow","Mecklenburg-Vorpommern","MV","","00","Vorpommern-Greifswald","13075","53.5358","13.8323","4"],"17033":["DE","17033","Neubrandenburg","Mecklenburg-Vorpommern","MV","","00","Mecklenburgische Seenplatte","13071","53.5476","13.2555","4"],"17034":["DE","17034","Neubrandenburg","Mecklenburg-Vorpommern","MV","","00","Mecklenburgische Seenplatte","13071","53.5761","13.2797","4"],"17036":["DE","17036","Neubrandenburg","Mecklenburg-Vorpommern","MV","","00","Mecklenburgische Seenplatte","13071","53.5537","13.2969","4"],"17039":["DE","17039","Neverin","Mecklenburg-Vorpommern","MV","","00","Mecklenburgische Seenplatte","13071","53.6207","13.3366","4"],"17087":["DE","17087","Altentreptow","Mecklenburg-Vorpommern","MV","","00","Mecklenburgische Seenplatte","13071","53.6942","13.265","4"],"17089":["DE","17089","Breest","Mecklenburg-Vorpommern","MV","","00","Mecklenburgische Seenplatte","13071","53.7902","13.3347","4"],"17091":["DE","17091","Pripsleben","Mecklenburg-Vorpommern","MV","","00","Mecklenburgische Seenplatte","13071","53.716","13.1864","4"],"17094":["DE","17094","Pragsdorf","Mecklenburg-Vorpommern","MV","","00","Mecklenburgische Seenplatte","13071","53.5388","13.3946","4"],"17098":["DE","17098","Friedland","Mecklenburg-Vorpommern","MV","","00","Mecklenburgische Seenplatte","13071","53.6703","13.554","4"],"17099":["DE","17099","Glienke","Mecklenburg-Vorpommern","MV","","00","Mecklenburgische Seenplatte","13071","53.5878","13.4306","4"],"17109":["DE","17109","Demmin","Mecklenburg-Vorpommern","MV","","00","Mecklenburgische Seenplatte","13071","53.9076","13.0314","4"],"17111":["DE","17111","Siedenbr\u00fcnzow","Mecklenburg-Vorpommern","MV","","00","Mecklenburgische Seenplatte","13071","53.897","13.1455","4"],"17121":["DE","17121","W\u00fcstenfelde","Mecklenburg-Vorpommern","MV","","00","Vorpommern-Greifswald","13075","53.9442","13.1451","4"],"17126":["DE","17126","Jarmen","Mecklenburg-Vorpommern","MV","","00","Vorpommern-Greifswald","13075","53.9239","13.3403","4"],"17129":["DE","17129","Tutow","Mecklenburg-Vorpommern","MV","","00","Vorpommern-Greifswald","13075","53.9157","13.2481","4"],"17139":["DE","17139","Schwinkendorf","Mecklenburg-Vorpommern","MV","","00","Mecklenburgische Seenplatte","13071","53.6427","12.684","4"],"17153":["DE","17153","Zettemin","Mecklenburg-Vorpommern","MV","","00","Mecklenburgische Seenplatte","13071","53.6474","12.8302","4"],"17154":["DE","17154","Neukalen","Mecklenburg-Vorpommern","MV","","00","Mecklenburgische Seenplatte","13071","53.8227","12.7901","4"],"17159":["DE","17159","Brudersdorf","Mecklenburg-Vorpommern","MV","","00","Mecklenburgische Seenplatte","13071","53.9537","12.879","4"],"17166":["DE","17166","Gro\u00df Wokern","Mecklenburg-Vorpommern","MV","","00","Landkreis Rostock","13072","53.7513","12.4925","4"],"17168":["DE","17168","J\u00f6rdenstorf","Mecklenburg-Vorpommern","MV","","00","Landkreis Rostock","13072","53.8782","12.6162","4"],"17179":["DE","17179","Boddin","Mecklenburg-Vorpommern","MV","","00","Landkreis Rostock","13072","53.9374","12.6468","4"],"17192":["DE","17192","Varchentin","Mecklenburg-Vorpommern","MV","","00","Mecklenburgische Seenplatte","13071","53.5841","12.8602","4"],"17194":["DE","17194","Vielist","Mecklenburg-Vorpommern","MV","","00","Mecklenburgische Seenplatte","13071","53.554","12.6388","4"],"17207":["DE","17207","Gotthun","Mecklenburg-Vorpommern","MV","","00","Mecklenburgische Seenplatte","13071","53.4164","12.5908","4"],"17209":["DE","17209","Jaebetz","Mecklenburg-Vorpommern","MV","","00","Mecklenburgische Seenplatte","13071","53.3198","12.3676","4"],"17213":["DE","17213","G\u00f6hren-Lebbin","Mecklenburg-Vorpommern","MV","","00","Mecklenburgische Seenplatte","13071","53.4794","12.511","4"],"17214":["DE","17214","Alt Schwerin","Mecklenburg-Vorpommern","MV","","00","Mecklenburgische Seenplatte","13071","53.5126","12.3464","4"],"17217":["DE","17217","Klein Lukow","Mecklenburg-Vorpommern","MV","","00","Mecklenburgische Seenplatte","13071","53.5345","13.0345","4"],"17219":["DE","17219","M\u00f6llenhagen","Mecklenburg-Vorpommern","MV","","00","Mecklenburgische Seenplatte","13071","53.5239","12.9287","4"],"17235":["DE","17235","Neustrelitz","Mecklenburg-Vorpommern","MV","","00","Mecklenburgische Seenplatte","13071","53.3613","13.0729","4"],"17237":["DE","17237","M\u00f6llenbeck","Mecklenburg-Vorpommern","MV","","00","Mecklenburgische Seenplatte","13071","53.3895","13.3423","4"],"17248":["DE","17248","L\u00e4rz","Mecklenburg-Vorpommern","MV","","00","Mecklenburgische Seenplatte","13071","53.2931","12.7466","4"],"17252":["DE","17252","Mirow","Mecklenburg-Vorpommern","MV","","00","Mecklenburgische Seenplatte","13071","53.2751","12.8154","4"],"17255":["DE","17255","Wesenberg","Mecklenburg-Vorpommern","MV","","00","Mecklenburgische Seenplatte","13071","53.2803","12.9694","4"],"17258":["DE","17258","Feldberger Seenlandschaft","Mecklenburg-Vorpommern","MV","","00","Mecklenburgische Seenplatte","13071","53.3391","13.4188","4"],"17259":["DE","17259","Feldberger Seenlandschaft","Mecklenburg-Vorpommern","MV","","00","Mecklenburgische Seenplatte","13071","53.3391","13.4188","4"],"17309":["DE","17309","Pasewalk","Mecklenburg-Vorpommern","MV","","00","Vorpommern-Greifswald","13075","53.5063","13.99","4"],"17321":["DE","17321","Ramin","Mecklenburg-Vorpommern","MV","","00","Vorpommern-Greifswald","13075","53.4131","14.2887","4"],"17322":["DE","17322","Blankensee","Mecklenburg-Vorpommern","MV","","00","Vorpommern-Greifswald","13075","53.5124","14.3063","4"],"17328":["DE","17328","Wollin","Mecklenburg-Vorpommern","MV","","00","Vorpommern-Greifswald","13075","53.3151","14.2173","4"],"17329":["DE","17329","Krackow","Mecklenburg-Vorpommern","MV","","00","Vorpommern-Greifswald","13075","53.344","14.2647","4"],"17335":["DE","17335","Strasburg","Mecklenburg-Vorpommern","MV","","00","Vorpommern-Greifswald","13075","53.5103","13.7451","4"],"17348":["DE","17348","Petersdorf","Mecklenburg-Vorpommern","MV","","00","Mecklenburgische Seenplatte","13071","53.4808","13.5138","4"],"17349":["DE","17349","Gro\u00df Miltzow","Mecklenburg-Vorpommern","MV","","00","Mecklenburgische Seenplatte","13071","53.5357","13.5935","4"],"17358":["DE","17358","Hammer","Mecklenburg-Vorpommern","MV","","00","Vorpommern-Greifswald","13075","53.6011","13.9804","4"],"17367":["DE","17367","Eggesin","Mecklenburg-Vorpommern","MV","","00","Vorpommern-Greifswald","13075","53.6797","14.0799","4"],"17373":["DE","17373","Ueckerm\u00fcnde","Mecklenburg-Vorpommern","MV","","00","Vorpommern-Greifswald","13075","53.7379","14.0447","4"],"17375":["DE","17375","Hintersee","Mecklenburg-Vorpommern","MV","","00","Vorpommern-Greifswald","13075","53.6308","14.2579","4"],"17379":["DE","17379","Wilhelmsburg","Mecklenburg-Vorpommern","MV","","00","Vorpommern-Greifswald","13075","53.6422","13.8582","4"],"17389":["DE","17389","Anklam","Mecklenburg-Vorpommern","MV","","00","Vorpommern-Greifswald","13075","53.8564","13.6897","4"],"17390":["DE","17390","Ziethen","Mecklenburg-Vorpommern","MV","","00","Vorpommern-Greifswald","13075","53.8878","13.6754","4"],"17391":["DE","17391","Liepen","Mecklenburg-Vorpommern","MV","","00","Vorpommern-Greifswald","13075","53.8857","13.467","4"],"17392":["DE","17392","Drewelow","Mecklenburg-Vorpommern","MV","","00","Vorpommern-Greifswald","13075","53.7687","13.5767","4"],"17398":["DE","17398","Ducherow","Mecklenburg-Vorpommern","MV","","00","Vorpommern-Greifswald","13075","53.7644","13.7822","4"],"17406":["DE","17406","Rankwitz","Mecklenburg-Vorpommern","MV","","00","Vorpommern-Greifswald","13075","53.9455","13.9268","4"],"17419":["DE","17419","Ahlbeck","Mecklenburg-Vorpommern","MV","","00","Vorpommern-Greifswald","13075","53.9333","14.2","4"],"17424":["DE","17424","Heringsdorf","Mecklenburg-Vorpommern","MV","","00","Vorpommern-Greifswald","13075","53.95","14.1667","4"],"17429":["DE","17429","Pudagla","Mecklenburg-Vorpommern","MV","","00","Vorpommern-Greifswald","13075","53.9692","14.0669","4"],"17438":["DE","17438","Wolgast","Mecklenburg-Vorpommern","MV","","00","Vorpommern-Greifswald","13075","54.0528","13.772","4"],"17440":["DE","17440","L\u00fctow","Mecklenburg-Vorpommern","MV","","00","Vorpommern-Greifswald","13075","54.0115","13.8792","4"],"17449":["DE","17449","Trassenheide","Mecklenburg-Vorpommern","MV","","00","Vorpommern-Greifswald","13075","54.0846","13.8648","4"],"17454":["DE","17454","Zinnowitz","Mecklenburg-Vorpommern","MV","","00","Vorpommern-Greifswald","13075","54.0667","13.9","4"],"17459":["DE","17459","Loddin","Mecklenburg-Vorpommern","MV","","00","Vorpommern-Greifswald","13075","54.0225","14.0075","4"],"17489":["DE","17489","Greifswald","Mecklenburg-Vorpommern","MV","","00","Vorpommern-Greifswald","13075","54.0881","13.3876","4"],"17491":["DE","17491","Greifswald","Mecklenburg-Vorpommern","MV","","00","Vorpommern-Greifswald","13075","54.083","13.4058","4"],"17493":["DE","17493","Greifswald","Mecklenburg-Vorpommern","MV","","00","Vorpommern-Greifswald","13075","54.0902","13.4464","4"],"17495":["DE","17495","Z\u00fcssow","Mecklenburg-Vorpommern","MV","","00","Vorpommern-Greifswald","13075","53.9771","13.5485","4"],"17498":["DE","17498","Weitenhagen","Mecklenburg-Vorpommern","MV","","00","Vorpommern-Greifswald","13075","54.0537","13.41","4"],"17506":["DE","17506","K\u00f6lzin","Mecklenburg-Vorpommern","MV","","00","Vorpommern-Greifswald","13075","53.9633","13.45","4"],"17509":["DE","17509","Kemnitz","Mecklenburg-Vorpommern","MV","","00","Vorpommern-Greifswald","13075","54.0772","13.5353","4"]}