{"25335":["DE","25335","Neuendorf bei Elmshorn","Schleswig-Holstein","SH","","00","Kreis Steinburg","01061","53.7333","9.5667","4"],"25336":["DE","25336","Elmshorn","Schleswig-Holstein","SH","","00","Kreis Pinneberg","01056","53.7491","9.6592","4"],"25337":["DE","25337","Elmshorn","Schleswig-Holstein","SH","","00","Kreis Pinneberg","01056","53.7494","9.685","4"],"25348":["DE","25348","Blomesche Wildnis","Schleswig-Holstein","SH","","00","Kreis Steinburg","01061","53.8","9.4167","4"],"25355":["DE","25355","Heede","Schleswig-Holstein","SH","","00","Kreis Pinneberg","01056","53.7833","9.8","4"],"25358":["DE","25358","Hohenfelde","Schleswig-Holstein","SH","","00","Kreis Steinburg","01061","53.8432","9.6226","4"],"25361":["DE","25361","Elskop","Schleswig-Holstein","SH","","00","Kreis Steinburg","01061","53.8167","9.4833","4"],"25364":["DE","25364","Brande-H\u00f6rnerkirchen","Schleswig-Holstein","SH","","00","Kreis Pinneberg","01056","53.85","9.7167","4"],"25365":["DE","25365","Klein Offenseth-Sparrieshoop","Schleswig-Holstein","SH","","00","Kreis Pinneberg","01056","53.7975","9.6865","4"],"25368":["DE","25368","Kiebitzreihe","Schleswig-Holstein","SH","","00","Kreis Steinburg","01061","53.7833","9.6167","4"],"25370":["DE","25370","Seester","Schleswig-Holstein","SH","","00","Kreis Pinneberg","01056","53.7178","9.598","4"],"25371":["DE","25371","Seesterm\u00fche","Schleswig-Holstein","SH","","00","Kreis Pinneberg","01056","53.7","9.5667","4"],"25373":["DE","25373","Ellerhoop","Schleswig-Holstein","SH","","00","Kreis Pinneberg","01056","53.726","9.7693","4"],"25376":["DE","25376","Krempdorf","Schleswig-Holstein","SH","","00","Kreis Steinburg","01061","53.8333","9.4667","4"],"25377":["DE","25377","Kollmar","Schleswig-Holstein","SH","","00","Kreis Steinburg","01061","53.7294","9.4788","4"],"25379":["DE","25379","Herzhorn","Schleswig-Holstein","SH","","00","Kreis Steinburg","01061","53.7833","9.4833","4"],"25404":["DE","25404","Pinneberg","Schleswig-Holstein","SH","","00","Kreis Pinneberg","01056","53.659","9.801","1"],"25421":["DE","25421","Pinneberg","Schleswig-Holstein","SH","","00","Kreis Pinneberg","01056","53.6591","9.8009","4"],"25429":["DE","25429","Uetersen","Schleswig-Holstein","SH","","00","Kreis Pinneberg","01056","53.6934","9.6542","4"],"25436":["DE","25436","Uetersen","Schleswig-Holstein","SH","","00","Kreis Pinneberg","01056","53.6865","9.6694","4"],"25437":["DE","25437","Tornesch","Schleswig-Holstein","SH","","00","Kreis Pinneberg","01056","53.7039","9.731","4"],"25451":["DE","25451","Quickborn","Schleswig-Holstein","SH","","00","Kreis Pinneberg","01056","53.7283","9.9093","4"],"25462":["DE","25462","Rellingen","Schleswig-Holstein","SH","","00","Kreis Pinneberg","01056","53.6413","9.8647","4"],"25469":["DE","25469","Halstenbek","Schleswig-Holstein","SH","","00","Kreis Pinneberg","01056","53.6333","9.85","4"],"25474":["DE","25474","Ellerbek","Schleswig-Holstein","SH","","00","Kreis Pinneberg","01056","53.6582","9.8699","4"],"25479":["DE","25479","Ellerau","Schleswig-Holstein","SH","","00","Kreis Segeberg","01060","53.75","9.9167","4"],"25482":["DE","25482","Appen","Schleswig-Holstein","SH","","00","Kreis Pinneberg","01056","53.6581","9.7458","4"],"25485":["DE","25485","Bilsen","Schleswig-Holstein","SH","","00","Kreis Pinneberg","01056","53.7667","9.8833","4"],"25486":["DE","25486","Alveslohe","Schleswig-Holstein","SH","","00","Kreis Segeberg","01060","53.7833","9.9167","4"],"25488":["DE","25488","Holm","Schleswig-Holstein","SH","","00","Kreis Pinneberg","01056","53.6167","9.6667","4"],"25489":["DE","25489","Haseldorf","Schleswig-Holstein","SH","","00","Kreis Pinneberg","01056","53.6378","9.5915","4"],"25491":["DE","25491","Hetlingen","Schleswig-Holstein","SH","","00","Kreis Pinneberg","01056","53.6071","9.6372","4"],"25492":["DE","25492","Heist","Schleswig-Holstein","SH","","00","Kreis Pinneberg","01056","53.65","9.65","4"],"25494":["DE","25494","Borstel-Hohenraden","Schleswig-Holstein","SH","","00","Kreis Pinneberg","01056","53.6833","9.8167","4"],"25495":["DE","25495","Kummerfeld","Schleswig-Holstein","SH","","00","Kreis Pinneberg","01056","53.6926","9.791","4"],"25497":["DE","25497","Prisdorf","Schleswig-Holstein","SH","","00","Kreis Pinneberg","01056","53.6833","9.75","4"],"25499":["DE","25499","Tangstedt","Schleswig-Holstein","SH","","00","Kreis Pinneberg","01056","53.6771","9.8488","4"],"25524":["DE","25524","Heiligenstedtenerkamp","Schleswig-Holstein","SH","","00","Kreis Steinburg","01061","53.8996","9.4681","4"],"25541":["DE","25541","Brunsb\u00fcttel","Schleswig-Holstein","SH","","00","Kreis Dithmarschen","01051","53.895","9.1048","4"],"25548":["DE","25548","Kellinghusen","Schleswig-Holstein","SH","","00","Kreis Steinburg","01061","53.952","9.7196","4"],"25551":["DE","25551","Winseldorf","Schleswig-Holstein","SH","","00","Kreis Steinburg","01061","53.9443","9.6063","4"],"25554":["DE","25554","Neuendorf-Sachsenbande","Schleswig-Holstein","SH","","00","Kreis Steinburg","01061","53.9667","9.3417",""],"25557":["DE","25557","Bendorf","Schleswig-Holstein","SH","","00","Kreis Rendsburg-Eckernf\u00f6rde","01058","54.0833","9.3833","4"],"25560":["DE","25560","Oldenborstel","Schleswig-Holstein","SH","","00","Kreis Steinburg","01061","54.0667","9.5167","4"],"25563":["DE","25563","Wrist","Schleswig-Holstein","SH","","00","Kreis Steinburg","01061","53.9333","9.7667","4"],"25566":["DE","25566","L\u00e4gerdorf","Schleswig-Holstein","SH","","00","Kreis Steinburg","01061","53.8833","9.5833","4"],"25569":["DE","25569","Kremperheide","Schleswig-Holstein","SH","","00","Kreis Steinburg","01061","53.8872","9.4781","4"],"25572":["DE","25572","B\u00fcttel","Schleswig-Holstein","SH","","00","Kreis Steinburg","01061","53.9","9.2333","4"],"25573":["DE","25573","Beidenfleth","Schleswig-Holstein","SH","","00","Kreis Steinburg","01061","53.8794","9.4131","4"],"25575":["DE","25575","Beringstedt","Schleswig-Holstein","SH","","00","Kreis Rendsburg-Eckernf\u00f6rde","01058","54.1167","9.5333","4"],"25576":["DE","25576","Brokdorf","Schleswig-Holstein","SH","","00","Kreis Steinburg","01061","53.8638","9.3231","4"],"25578":["DE","25578","D\u00e4geling","Schleswig-Holstein","SH","","00","Kreis Steinburg","01061","53.8833","9.5333","4"],"25579":["DE","25579","Fitzbek","Schleswig-Holstein","SH","","00","Kreis Steinburg","01061","54","9.7667","4"],"25581":["DE","25581","Hennstedt","Schleswig-Holstein","SH","","00","Kreis Steinburg","01061","54.0333","9.7167","4"],"25582":["DE","25582","Hohenaspe","Schleswig-Holstein","SH","","00","Kreis Steinburg","01061","53.989","9.5277","4"],"25584":["DE","25584","Holstenniendorf","Schleswig-Holstein","SH","","00","Kreis Steinburg","01061","54.0416","9.3481","4"],"25585":["DE","25585","L\u00fctjenwestedt","Schleswig-Holstein","SH","","00","Kreis Rendsburg-Eckernf\u00f6rde","01058","54.1333","9.4833","4"],"25587":["DE","25587","M\u00fcnsterdorf","Schleswig-Holstein","SH","","00","Kreis Steinburg","01061","53.9023","9.5412","4"],"25588":["DE","25588","Mehlbek","Schleswig-Holstein","SH","","00","Kreis Steinburg","01061","54.0046","9.4345","4"],"25590":["DE","25590","Osterstedt","Schleswig-Holstein","SH","","00","Kreis Rendsburg-Eckernf\u00f6rde","01058","54.1082","9.5744","4"],"25591":["DE","25591","Ottenb\u00fcttel","Schleswig-Holstein","SH","","00","Kreis Steinburg","01061","53.9711","9.5042","4"],"25593":["DE","25593","Christinenthal","Schleswig-Holstein","SH","","00","Kreis Steinburg","01061","54.05","9.5333","4"],"25594":["DE","25594","Vaalermoor","Schleswig-Holstein","SH","","00","Kreis Steinburg","01061","53.9851","9.3391","4"],"25596":["DE","25596","Bokelrehm","Schleswig-Holstein","SH","","00","Kreis Steinburg","01061","54.0382","9.3861","4"],"25597":["DE","25597","Moordiek","Schleswig-Holstein","SH","","00","Kreis Steinburg","01061","53.914","9.6534","4"],"25599":["DE","25599","Wewelsfleth","Schleswig-Holstein","SH","","00","Kreis Steinburg","01061","53.85","9.4","4"],"25693":["DE","25693","Sankt Michaelisdonn","Schleswig-Holstein","SH","","00","Kreis Dithmarschen","01051","53.9833","9.1167","4"],"25704":["DE","25704","Nordermeldorf","Schleswig-Holstein","SH","","00","Kreis Dithmarschen","01051","54.1167","9.0167","4"],"25709":["DE","25709","Helse","Schleswig-Holstein","SH","","00","Kreis Dithmarschen","01051","53.9746","9.0104","4"],"25712":["DE","25712","Brickeln","Schleswig-Holstein","SH","","00","Kreis Dithmarschen","01051","54.0167","9.2333","4"],"25715":["DE","25715","Ramhusen","Schleswig-Holstein","SH","","00","Kreis Dithmarschen","01051","53.95","9.0833","4"],"25718":["DE","25718","Friedrichskoog","Schleswig-Holstein","SH","","00","Kreis Dithmarschen","01051","54.0167","8.9167","4"],"25719":["DE","25719","Barlt","Schleswig-Holstein","SH","","00","Kreis Dithmarschen","01051","54.0167","9.05","4"],"25721":["DE","25721","Eggstedt","Schleswig-Holstein","SH","","00","Kreis Dithmarschen","01051","54.05","9.2667","4"],"25724":["DE","25724","Neufeld","Schleswig-Holstein","SH","","00","Kreis Dithmarschen","01051","53.9","9.0167","4"],"25725":["DE","25725","Bornholt","Schleswig-Holstein","SH","","00","Kreis Rendsburg-Eckernf\u00f6rde","01058","54.1","9.3333","4"],"25727":["DE","25727","Frestedt","Schleswig-Holstein","SH","","00","Kreis Dithmarschen","01051","54.0333","9.1833","4"],"25729":["DE","25729","Windbergen","Schleswig-Holstein","SH","","00","Kreis Dithmarschen","01051","54.05","9.1167","4"],"25746":["DE","25746","Lohe-Rickelshof","Schleswig-Holstein","SH","","00","Kreis Dithmarschen","01051","54.188","9.0707","4"],"25761":["DE","25761","Westerdeichstrich","Schleswig-Holstein","SH","","00","Kreis Dithmarschen","01051","54.1615","8.8644","4"],"25764":["DE","25764","Wesselburener-Deichhausen","Schleswig-Holstein","SH","","00","Kreis Dithmarschen","01051","54.1667","8.9333",""],"25767":["DE","25767","Arkebek","Schleswig-Holstein","SH","","00","Kreis Dithmarschen","01051","54.1667","9.25","4"],"25770":["DE","25770","Hemmingstedt","Schleswig-Holstein","SH","","00","Kreis Dithmarschen","01051","54.15","9.0667","4"],"25774":["DE","25774","Lehe","Schleswig-Holstein","SH","","00","Kreis Dithmarschen","01051","54.3414","9.0237","4"],"25776":["DE","25776","Rehm-Flehde-Bargen","Schleswig-Holstein","SH","","00","Kreis Dithmarschen","01051","54.2833","9.0167","4"],"25779":["DE","25779","Fedderingen","Schleswig-Holstein","SH","","00","Kreis Dithmarschen","01051","54.2833","9.1333","4"],"25782":["DE","25782","Schrum","Schleswig-Holstein","SH","","00","Kreis Dithmarschen","01051","54.1833","9.25","4"],"25785":["DE","25785","Sarzb\u00fcttel","Schleswig-Holstein","SH","","00","Kreis Dithmarschen","01051","54.1167","9.1833","4"],"25786":["DE","25786","Dellstedt","Schleswig-Holstein","SH","","00","Kreis Dithmarschen","01051","54.2333","9.3667","4"],"25788":["DE","25788","Delve","Schleswig-Holstein","SH","","00","Kreis Dithmarschen","01051","54.3","9.25","4"],"25791":["DE","25791","Barkenholm","Schleswig-Holstein","SH","","00","Kreis Dithmarschen","01051","54.2333","9.1833","4"],"25792":["DE","25792","Neuenkirchen","Schleswig-Holstein","SH","","00","Kreis Dithmarschen","01051","54.2365","8.9915","4"],"25794":["DE","25794","Pahlen","Schleswig-Holstein","SH","","00","Kreis Dithmarschen","01051","54.2667","9.3","4"],"25795":["DE","25795","Weddingstedt","Schleswig-Holstein","SH","","00","Kreis Dithmarschen","01051","54.2343","9.091","4"],"25797":["DE","25797","W\u00f6hrden","Schleswig-Holstein","SH","","00","Kreis Dithmarschen","01051","54.1667","9","4"],"25799":["DE","25799","Wrohm","Schleswig-Holstein","SH","","00","Kreis Dithmarschen","01051","54.2131","9.3821","4"],"25813":["DE","25813","Schwesing","Schleswig-Holstein","SH","","00","Kreis Nordfriesland","01054","54.4948","9.135","4"],"25821":["DE","25821","Vollstedt","Schleswig-Holstein","SH","","00","Kreis Nordfriesland","01054","54.6167","9.0333","4"],"25826":["DE","25826","Sankt Peter-Ording","Schleswig-Holstein","SH","","00","Kreis Nordfriesland","01054","54.3036","8.6414","4"],"25832":["DE","25832","Kotzenb\u00fcll","Schleswig-Holstein","SH","","00","Kreis Nordfriesland","01054","54.3333","8.9045","4"],"25836":["DE","25836","Katharinenheerd","Schleswig-Holstein","SH","","00","Kreis Nordfriesland","01054","54.3333","8.8333","4"],"25840":["DE","25840","Koldenb\u00fcttel","Schleswig-Holstein","SH","","00","Kreis Nordfriesland","01054","54.3833","9.0667","4"],"25842":["DE","25842","Ockholm","Schleswig-Holstein","SH","","00","Kreis Nordfriesland","01054","54.6667","8.8333","4"],"25845":["DE","25845","Nordstrand","Schleswig-Holstein","SH","","00","Kreis Nordfriesland","01054","54.4968","8.8869",""],"25849":["DE","25849","Pellworm","Schleswig-Holstein","SH","","00","Kreis Nordfriesland","01054","54.5161","8.6451","4"],"25850":["DE","25850","Bondelum","Schleswig-Holstein","SH","","00","Kreis Nordfriesland","01054","54.5667","9.2667","4"],"25852":["DE","25852","Bordelum","Schleswig-Holstein","SH","","00","Kreis Nordfriesland","01054","54.6333","8.9333","4"],"25853":["DE","25853","Drelsdorf","Schleswig-Holstein","SH","","00","Kreis Nordfriesland","01054","54.65","9.05",""],"25855":["DE","25855","Haselund","Schleswig-Holstein","SH","","00","Kreis Nordfriesland","01054","54.6","9.1833","4"],"25856":["DE","25856","Hattstedtermarsch","Schleswig-Holstein","SH","","00","Kreis Nordfriesland","01054","54.55","9","4"],"25858":["DE","25858","H\u00f6gel","Schleswig-Holstein","SH","","00","Kreis Nordfriesland","01054","54.65","9.0667","4"],"25859":["DE","25859","Hooge","Schleswig-Holstein","SH","","00","Kreis Nordfriesland","01054","54.57","8.5481","4"],"25860":["DE","25860","Arlewatt","Schleswig-Holstein","SH","","00","Kreis Nordfriesland","01054","54.5333","9.0833","4"],"25862":["DE","25862","Joldelund","Schleswig-Holstein","SH","","00","Kreis Nordfriesland","01054","54.65","9.1333","4"],"25863":["DE","25863","Langene\u00df","Schleswig-Holstein","SH","","00","Kreis Nordfriesland","01054","54.6333","8.6333",""],"25864":["DE","25864","L\u00f6wenstedt","Schleswig-Holstein","SH","","00","Kreis Nordfriesland","01054","54.6216","9.1726","4"],"25866":["DE","25866","Mildstedt","Schleswig-Holstein","SH","","00","Kreis Nordfriesland","01054","54.4667","9.1","4"],"25868":["DE","25868","Norderstapel","Schleswig-Holstein","SH","","00","Kreis Schleswig-Flensburg","01059","54.36","9.2408","4"],"25869":["DE","25869","Gr\u00f6de","Schleswig-Holstein","SH","","00","Kreis Nordfriesland","01054","54.6333","8.7167","4"],"25870":["DE","25870","Oldenswort","Schleswig-Holstein","SH","","00","Kreis Nordfriesland","01054","54.3724","8.94","4"],"25872":["DE","25872","Ostenfeld","Schleswig-Holstein","SH","","00","Kreis Nordfriesland","01054","54.464","9.2343","4"],"25873":["DE","25873","Rantrum","Schleswig-Holstein","SH","","00","Kreis Nordfriesland","01054","54.4406","9.1287","4"],"25875":["DE","25875","Schob\u00fcll","Schleswig-Holstein","SH","","00","Kreis Nordfriesland","01054","54.5092","9.0062","4"],"25876":["DE","25876","Schwabstedt","Schleswig-Holstein","SH","","00","Kreis Nordfriesland","01054","54.397","9.1865","4"],"25878":["DE","25878","Drage","Schleswig-Holstein","SH","","00","Kreis Nordfriesland","01054","54.3556","9.1578","4"],"25879":["DE","25879","S\u00fcderstapel","Schleswig-Holstein","SH","","00","Kreis Schleswig-Flensburg","01059","54.35","9.2167","4"],"25881":["DE","25881","Tating","Schleswig-Holstein","SH","","00","Kreis Nordfriesland","01054","54.3261","8.708","4"],"25882":["DE","25882","Tetenb\u00fcll","Schleswig-Holstein","SH","","00","Kreis Nordfriesland","01054","54.3521","8.8279","4"],"25884":["DE","25884","Sollwitt","Schleswig-Holstein","SH","","00","Kreis Nordfriesland","01054","54.6","9.2167","4"],"25885":["DE","25885","Wester-Ohrstedt","Schleswig-Holstein","SH","","00","Kreis Nordfriesland","01054","54.508","9.1857","4"],"25887":["DE","25887","Winnert","Schleswig-Holstein","SH","","00","Kreis Nordfriesland","01054","54.4333","9.2","4"],"25889":["DE","25889","Uelvesb\u00fcll","Schleswig-Holstein","SH","","00","Kreis Nordfriesland","01054","54.4153","8.9239","4"],"25899":["DE","25899","Dageb\u00fcll","Schleswig-Holstein","SH","","00","Kreis Nordfriesland","01054","54.7293","8.7008","4"],"25917":["DE","25917","Tinningstedt","Schleswig-Holstein","SH","","00","Kreis Nordfriesland","01054","54.8167","8.9333","4"],"25920":["DE","25920","Stedesand","Schleswig-Holstein","SH","","00","Kreis Nordfriesland","01054","54.7386","8.9275","4"],"25923":["DE","25923","Holm","Schleswig-Holstein","SH","","00","Kreis Nordfriesland","01054","54.8333","8.8667","4"],"25924":["DE","25924","Emmelsb\u00fcll-Horsb\u00fcll","Schleswig-Holstein","SH","","00","Kreis Nordfriesland","01054","54.8167","8.7","4"],"25926":["DE","25926","Bramstedtlund","Schleswig-Holstein","SH","","00","Kreis Nordfriesland","01054","54.85","9.0667","4"],"25927":["DE","25927","Neukirchen","Schleswig-Holstein","SH","","00","Kreis Nordfriesland","01054","54.8667","8.7333","4"],"25938":["DE","25938","Witsum","Schleswig-Holstein","SH","","00","Kreis Nordfriesland","01054","54.6995","8.4406","4"],"25946":["DE","25946","Wittd\u00fcn","Schleswig-Holstein","SH","","00","Kreis Nordfriesland","01054","54.627","8.3893","4"],"25980":["DE","25980","Sylt-Ost","Schleswig-Holstein","SH","","00","Kreis Nordfriesland","01054","54.8611","8.4114","4"],"25992":["DE","25992","List","Schleswig-Holstein","SH","","00","Kreis Nordfriesland","01054","55.0192","8.4313","4"],"25996":["DE","25996","Wenningstedt","Schleswig-Holstein","SH","","00","Kreis Nordfriesland","01054","54.9358","8.33","4"],"25997":["DE","25997","H\u00f6rnum","Schleswig-Holstein","SH","","00","Kreis Nordfriesland","01054","54.7573","8.2883","4"],"25999":["DE","25999","Kampen","Schleswig-Holstein","SH","","00","Kreis Nordfriesland","01054","54.9541","8.3417","4"]}